enrRiceTrait/Enrichment.py
enrRiceTrait/PTE_config.py
enrRiceTrait/__init__.py
enrRiceTrait/data/Total_Association.txt
enrRiceTrait/data/to.wto.ro.funRiceGene.obo
enrRiceTrait-1.4.4.dist-info/LICENSE
enrRiceTrait-1.4.4.dist-info/METADATA
enrRiceTrait-1.4.4.dist-info/WHEEL
enrRiceTrait-1.4.4.dist-info/top_level.txt
enrRiceTrait-1.4.4.dist-info/RECORD
