Metadata-Version: 2.1
Name: enrRiceTrait
Version: 1.4.4
Summary: A python package for Rice Trait Enrichment.
Home-page: https://github.com/YaoXinZhi/enrRiceTrait
Author: xinzhi_yao
Author-email: xinzhi_bioinfo@163.com
License: UNKNOWN
Platform: UNKNOWN
Classifier: Programming Language :: Python :: 3
Classifier: License :: OSI Approved :: MIT License
Classifier: Operating System :: OS Independent
Requires-Python: >3.7
